{"nodes": [{"id": "home_g_projects_rexconverter_internal_rexengine_types_go", "label": "types.go", "file_type": "code", "source_file": "internal/rexengine/types.go", "source_location": "L1"}, {"id": "rexengine_rexmetadata", "label": "RexMetadata", "file_type": "code", "source_file": "internal/rexengine/types.go", "source_location": "L4"}, {"id": "rexengine_wavcuemarker", "label": "WavCueMarker", "file_type": "code", "source_file": "internal/rexengine/types.go", "source_location": "L18"}, {"id": "rexengine_sliceextraction", "label": "SliceExtraction", "file_type": "code", "source_file": "internal/rexengine/types.go", "source_location": "L25"}, {"id": "rexengine_pipelineconfig", "label": "PipelineConfig", "file_type": "code", "source_file": "internal/rexengine/types.go", "source_location": "L33"}], "edges": [{"source": "home_g_projects_rexconverter_internal_rexengine_types_go", "target": "rexengine_rexmetadata", "relation": "contains", "confidence": "EXTRACTED", "source_file": "internal/rexengine/types.go", "source_location": "L4", "weight": 1.0}, {"source": "home_g_projects_rexconverter_internal_rexengine_types_go", "target": "rexengine_wavcuemarker", "relation": "contains", "confidence": "EXTRACTED", "source_file": "internal/rexengine/types.go", "source_location": "L18", "weight": 1.0}, {"source": "home_g_projects_rexconverter_internal_rexengine_types_go", "target": "rexengine_sliceextraction", "relation": "contains", "confidence": "EXTRACTED", "source_file": "internal/rexengine/types.go", "source_location": "L25", "weight": 1.0}, {"source": "rexengine_sliceextraction", "target": "rexengine_rexmetadata", "relation": "references", "confidence": "EXTRACTED", "source_file": "internal/rexengine/types.go", "source_location": "L26", "weight": 1.0, "context": "field"}, {"source": "rexengine_sliceextraction", "target": "rexengine_wavcuemarker", "relation": "references", "confidence": "EXTRACTED", "source_file": "internal/rexengine/types.go", "source_location": "L27", "weight": 1.0, "context": "field"}, {"source": "home_g_projects_rexconverter_internal_rexengine_types_go", "target": "rexengine_pipelineconfig", "relation": "contains", "confidence": "EXTRACTED", "source_file": "internal/rexengine/types.go", "source_location": "L33", "weight": 1.0}], "raw_calls": []}